pydantic_ai/__init__.py
pydantic_ai/__main__.py
pydantic_ai/_a2a.py
pydantic_ai/_agent_graph.py
pydantic_ai/_function_schema.py
pydantic_ai/_griffe.py
pydantic_ai/_instrumentation.py
pydantic_ai/_json_schema.py
pydantic_ai/_mcp.py
pydantic_ai/_otel_messages.py
pydantic_ai/_output.py
pydantic_ai/_parts_manager.py
pydantic_ai/_run_context.py
pydantic_ai/_system_prompt.py
pydantic_ai/_thinking_part.py
pydantic_ai/_tool_manager.py
pydantic_ai/_utils.py
pydantic_ai/ag_ui.py
pydantic_ai/builtin_tools.py
pydantic_ai/direct.py
pydantic_ai/exceptions.py
pydantic_ai/format_prompt.py
pydantic_ai/mcp.py
pydantic_ai/messages.py
pydantic_ai/output.py
pydantic_ai/py.typed
pydantic_ai/result.py
pydantic_ai/retries.py
pydantic_ai/run.py
pydantic_ai/settings.py
pydantic_ai/tools.py
pydantic_ai/usage.py
pydantic_ai/_cli/__init__.py
pydantic_ai/_cli/web.py
pydantic_ai/agent/__init__.py
pydantic_ai/agent/abstract.py
pydantic_ai/agent/wrapper.py
pydantic_ai/common_tools/__init__.py
pydantic_ai/common_tools/duckduckgo.py
pydantic_ai/common_tools/exa.py
pydantic_ai/common_tools/tavily.py
pydantic_ai/durable_exec/__init__.py
pydantic_ai/durable_exec/dbos/__init__.py
pydantic_ai/durable_exec/dbos/_agent.py
pydantic_ai/durable_exec/dbos/_fastmcp_toolset.py
pydantic_ai/durable_exec/dbos/_mcp.py
pydantic_ai/durable_exec/dbos/_mcp_server.py
pydantic_ai/durable_exec/dbos/_model.py
pydantic_ai/durable_exec/dbos/_utils.py
pydantic_ai/durable_exec/prefect/__init__.py
pydantic_ai/durable_exec/prefect/_agent.py
pydantic_ai/durable_exec/prefect/_cache_policies.py
pydantic_ai/durable_exec/prefect/_function_toolset.py
pydantic_ai/durable_exec/prefect/_mcp_server.py
pydantic_ai/durable_exec/prefect/_model.py
pydantic_ai/durable_exec/prefect/_toolset.py
pydantic_ai/durable_exec/prefect/_types.py
pydantic_ai/durable_exec/temporal/__init__.py
pydantic_ai/durable_exec/temporal/_agent.py
pydantic_ai/durable_exec/temporal/_dynamic_toolset.py
pydantic_ai/durable_exec/temporal/_fastmcp_toolset.py
pydantic_ai_slim-1.50.0.dist-info/METADATA
pydantic_ai_slim-1.50.0.dist-info/WHEEL
pydantic_ai_slim-1.50.0.dist-info/entry_points.txt
pydantic_ai_slim-1.50.0.dist-info/licenses/LICENSE
pydantic_ai_slim-1.50.0.dist-info/RECORD
